textwrapper.py
textwrapper-1.0.2.dist-info/LICENSE
textwrapper-1.0.2.dist-info/METADATA
textwrapper-1.0.2.dist-info/WHEEL
textwrapper-1.0.2.dist-info/entry_points.txt
textwrapper-1.0.2.dist-info/top_level.txt
textwrapper-1.0.2.dist-info/RECORD
